FNGameServer/GameModeBase.py
FNGameServer/GameSession.py
FNGameServer/Level.py
FNGameServer/NetConnection.py
FNGameServer/PackageMapClient.py
FNGameServer/PlayerController.py
FNGameServer/World.py
FNGameServer/__init__.py
FNGameServer/Classes/Channel.py
FNGameServer/Classes/NetConnection.py
FNGameServer/Classes/__init__.py
FNGameServer/Misc/NetworkVersion.py
FNGameServer/Misc/__init__.py
FNGameServer/Net/DataBunch.py
FNGameServer/Net/DataChannel.py
FNGameServer/Net/__init__.py
FNGameServer/PacketHandlers/StatelessConnectHandlerComponent.py
FNGameServer/PacketHandlers/__init__.py
FNGameServer/Serialization/BitReader.py
FNGameServer/Serialization/BitWriter.py
FNGameServer/Serialization/__init__.py
FNGameServer/UObject/CoreNet.py
FNGameServer/UObject/CoreNetTypes.py
FNGameServer/UObject/__init__.py
FNGameServer-0.0.2.dist-info/METADATA
FNGameServer-0.0.2.dist-info/WHEEL
FNGameServer-0.0.2.dist-info/top_level.txt
FNGameServer-0.0.2.dist-info/RECORD
