Metadata-Version: 2.1
Name: FNGameServer
Version: 0.0.2
Summary: UNKNOWN
Home-page: https://github.com/EZFNDEV/FortniteGameserver
Author: EZFN.DEV
Author-email: admin@ezfn.dev
License: Creative Commons Attribution-NonCommercial-NoDerivatives 4.0 International Public License
Platform: UNKNOWN
Requires-Dist: asyncio-dgram
Requires-Dist: bitarray
Requires-Dist: bitstring
